Metadata-Version: 2.1
Name: palace_webpub_manifest_parser
Version: 4.1.0
Summary: A parser for the Readium Web Publication Manifest, OPDS 2.0 and ODL formats.
Home-page: https://github.com/ThePalaceProject/webpub-manifest-parser
License: Apache-2.0
Keywords: ODL,OPDS 2.0,Open Publication Distribution System 2.0,Readium Web Publication Manifest,RWPM
Author: The Palace Project
Author-email: info@thepalaceproject.org
Requires-Python: >=3.8,<4
Classifier: Intended Audience :: Developers
Classifier: License :: OSI Approved :: Apache Software License
Classifier: Operating System :: OS Independent
Classifier: Programming Language :: Python
Classifier: Programming Language :: Python :: 3
Classifier: Programming Language :: Python :: 3.8
Classifier: Programming Language :: Python :: 3.9
Classifier: Programming Language :: Python :: 3.10
Classifier: Programming Language :: Python :: 3.11
Classifier: Programming Language :: Python :: 3.7
Classifier: Programming Language :: Python :: Implementation :: CPython
Classifier: Topic :: Software Development :: Libraries :: Python Modules
Requires-Dist: jsonschema (>=4.19,<5.0)
Requires-Dist: multipledispatch (>=1.0,<2.0)
Requires-Dist: pyrsistent (>=0.20,<0.21)
Requires-Dist: python-dateutil (>=2.8,<3.0)
Requires-Dist: pytz (>=2024.1,<2025.0)
Requires-Dist: requests (>=2.27,<3.0)
Requires-Dist: rfc3987 (>=1.3,<2.0)
Requires-Dist: uritemplate (>=4.1,<5.0)
Project-URL: Repository, https://github.com/ThePalaceProject/webpub-manifest-parser
